iron_worker.py
testDir/hello.py
iron_worker-1.3.8.dist-info/LICENSE.txt
iron_worker-1.3.8.dist-info/METADATA
iron_worker-1.3.8.dist-info/WHEEL
iron_worker-1.3.8.dist-info/top_level.txt
iron_worker-1.3.8.dist-info/RECORD
